stockmarketmba/__init__.py
stockmarketmba/config.ini
stockmarketmba/headers.json
stockmarketmba/lib.py
stockmarketmba/stockmarketmba.py
stockmarketmba-1.0.12.dist-info/LICENSE
stockmarketmba-1.0.12.dist-info/METADATA
stockmarketmba-1.0.12.dist-info/WHEEL
stockmarketmba-1.0.12.dist-info/top_level.txt
stockmarketmba-1.0.12.dist-info/RECORD
