Metadata-Version: 2.1
Name: stockmarketmba
Version: 1.0.12
Summary: UNKNOWN
License: UNKNOWN
Platform: UNKNOWN
License-File: LICENSE
Requires-Dist: async-generator (==1.10)
Requires-Dist: attrs (==21.2.0)
Requires-Dist: autopep8 (==1.6.0)
Requires-Dist: beautifulsoup4 (==4.10.0)
Requires-Dist: bleach (==4.1.0)
Requires-Dist: certifi (==2021.10.8)
Requires-Dist: cffi (==1.15.0)
Requires-Dist: charset-normalizer (==2.0.11)
Requires-Dist: click (==8.0.3)
Requires-Dist: colorama (==0.4.4)
Requires-Dist: cryptography (==35.0.0)
Requires-Dist: docutils (==0.18.1)
Requires-Dist: filelock (==3.4.2)
Requires-Dist: h11 (==0.12.0)
Requires-Dist: idna (==3.3)
Requires-Dist: importlib-metadata (==4.10.1)
Requires-Dist: keyring (==23.5.0)
Requires-Dist: lxml (==4.7.1)
Requires-Dist: openfigi (==0.0.9)
Requires-Dist: outcome (==1.1.0)
Requires-Dist: packaging (==21.3)
Requires-Dist: pkginfo (==1.8.2)
Requires-Dist: pycodestyle (==2.8.0)
Requires-Dist: pycparser (==2.21)
Requires-Dist: Pygments (==2.11.2)
Requires-Dist: pyOpenSSL (==21.0.0)
Requires-Dist: pyparsing (==3.0.7)
Requires-Dist: readme-renderer (==32.0)
Requires-Dist: requests (==2.27.1)
Requires-Dist: requests-file (==1.5.1)
Requires-Dist: requests-toolbelt (==0.9.1)
Requires-Dist: rfc3986 (==2.0.0)
Requires-Dist: selenium (==3.141.0)
Requires-Dist: selenium-requests (==1.3.3)
Requires-Dist: six (==1.16.0)
Requires-Dist: sniffio (==1.2.0)
Requires-Dist: sortedcontainers (==2.4.0)
Requires-Dist: soupsieve (==2.3.1)
Requires-Dist: tldextract (==3.1.2)
Requires-Dist: toml (==0.10.2)
Requires-Dist: tqdm (==4.62.3)
Requires-Dist: trio (==0.19.0)
Requires-Dist: trio-websocket (==0.9.2)
Requires-Dist: twine (==3.7.1)
Requires-Dist: urllib3 (==1.26.8)
Requires-Dist: webencodings (==0.5.1)
Requires-Dist: wsproto (==1.0.0)
Requires-Dist: zipp (==3.7.0)
